streetscope/__init__.py
streetscope/cv/__init__.py
streetscope/cv/segmentation/__init__.py
streetscope/cv/segmentation/segmentation.py
streetscope/download/__init__.py
streetscope/download/streetview_downloader.py
streetscope/download/utils/UserAgent.csv
streetscope/download/utils/__init__.py
streetscope/download/utils/geoprocess.py
streetscope/download/utils/get_pids.py
streetscope/download/utils/imtool.py
streetscope/streetscope.py
streetscope/transform/__init__.py
streetscope/transform/transform_image.py
streetscope-0.3.9.dist-info/LICENSE
streetscope-0.3.9.dist-info/METADATA
streetscope-0.3.9.dist-info/WHEEL
streetscope-0.3.9.dist-info/RECORD
