Metadata-Version: 2.1
Name: streetscope
Version: 0.3.9
Summary: This package handles downloading, cleaning, analyzing street view imagery
License: MIT
Author: koito19960406
Requires-Python: >=3.9,<4.0
Classifier: License :: OSI Approved :: MIT License
Classifier: Programming Language :: Python :: 3
Classifier: Programming Language :: Python :: 3.9
Classifier: Programming Language :: Python :: 3.10
Classifier: Programming Language :: Python :: 3.11
Requires-Dist: Pillow (>=8.3.2,<9.6)
Requires-Dist: Shapely (>=1.7.1,<2.0.0)
Requires-Dist: geopandas (>=0.9.0,<0.10.0)
Requires-Dist: geopy (>=2.2.0,<3.0.0)
Requires-Dist: numpy (>=1.21.2,<2.0.0)
Requires-Dist: opencv_python (>=4.5.3,<5.0.0)
Requires-Dist: osmnx (>=1.1.1,<2.0.0)
Requires-Dist: pandas (>=1.3.3,<2.0.0)
Requires-Dist: requests (>=2.30.0,<3.0.0)
Requires-Dist: scipy (>=1.7.1,<2.0.0)
Requires-Dist: setuptools (>=58.0.4,<59.0.0)
Requires-Dist: torch (>=2.0.0,<3.0.0)
Requires-Dist: tqdm (>=4.62.2,<5.0.0)
Requires-Dist: transformers (>=4.10.2,<5.0.0)
